{"properties": [
  {
    "name": "sr_address",
    "type": "java.lang.String",
    "description": "A description for 'sr_address'"
  },
  {
    "name": "event_publishing_tolerance",
    "type": "java.lang.Long",
    "description": "A description for 'event_publishing_tolerance'"
  },
  {
    "name": "remove_old_filters",
    "type": "java.lang.Boolean",
    "description": "A description for 'remove_old_filters'"
  },
  {
    "name": "check_interval",
    "type": "java.lang.Long",
    "description": "A description for 'check_interval'"
  },
  {
    "name": "sr_port",
    "type": "java.lang.Integer",
    "description": "A description for 'sr_port'"
  },
  {
    "name": "disable.hostname.verifier",
    "type": "java.lang.Boolean",
    "description": "A description for 'disable.hostname.verifier'"
  }
]}